aria2p-0.12.0.dist-info/METADATA
aria2p-0.12.0.dist-info/WHEEL
aria2p-0.12.0.dist-info/entry_points.txt
aria2p-0.12.0.dist-info/licenses/LICENSE
aria2p/__init__.py
aria2p/__main__.py
aria2p/api.py
aria2p/cli/__init__.py
aria2p/cli/commands/__init__.py
aria2p/cli/commands/add.py
aria2p/cli/commands/add_magnet.py
aria2p/cli/commands/add_metalink.py
aria2p/cli/commands/add_torrent.py
aria2p/cli/commands/call.py
aria2p/cli/commands/listen.py
aria2p/cli/commands/pause.py
aria2p/cli/commands/purge.py
aria2p/cli/commands/remove.py
aria2p/cli/commands/resume.py
aria2p/cli/commands/show.py
aria2p/cli/commands/top.py
aria2p/cli/main.py
aria2p/cli/parser.py
aria2p/client.py
aria2p/debug.py
aria2p/downloads.py
aria2p/interface.py
aria2p/options.py
aria2p/py.typed
aria2p/stats.py
aria2p/utils.py
aria2p-0.12.0.dist-info/RECORD
