Metadata-Version: 2.1
Name: aria2p
Version: 0.12.0
Summary: Command-line tool and library to interact with an aria2c daemon process with JSON-RPC.
Keywords: aria2 aria2c aria2-cli
Author-Email: Timothée Mazzucotelli <pawamoy@pm.me>
License: ISC
Classifier: Development Status :: 4 - Beta
Classifier: Intended Audience :: Developers
Classifier: Programming Language :: Python
Classifier: Programming Language :: Python :: 3
Classifier: Programming Language :: Python :: 3 :: Only
Classifier: Programming Language :: Python :: 3.8
Classifier: Programming Language :: Python :: 3.9
Classifier: Programming Language :: Python :: 3.10
Classifier: Programming Language :: Python :: 3.11
Classifier: Programming Language :: Python :: 3.12
Classifier: Topic :: Utilities
Classifier: Typing :: Typed
Project-URL: Homepage, https://pawamoy.github.io/aria2p
Project-URL: Documentation, https://pawamoy.github.io/aria2p
Project-URL: Changelog, https://pawamoy.github.io/aria2p/changelog
Project-URL: Repository, https://github.com/pawamoy/aria2p
Project-URL: Issues, https://github.com/pawamoy/aria2p/issues
Project-URL: Discussions, https://github.com/pawamoy/aria2p/discussions
Project-URL: Gitter, https://gitter.im/aria2p/community
Project-URL: Funding, https://github.com/sponsors/pawamoy
Requires-Python: >=3.8
Requires-Dist: appdirs>=1.4
Requires-Dist: loguru>=0.5
Requires-Dist: requests>=2.19
Requires-Dist: tomli>=2.0; python_version < "3.11"
Requires-Dist: websocket-client>=0.58
Requires-Dist: asciimatics>=1.13; extra == "tui"
Requires-Dist: pyperclip>=1.8; extra == "tui"
Provides-Extra: tui
